_recoil.cpython-310-darwin.so
recoil/__init__.py
pyrecoil-0.3.11.dist-info/COPYING
pyrecoil-0.3.11.dist-info/METADATA
pyrecoil-0.3.11.dist-info/WHEEL
pyrecoil-0.3.11.dist-info/top_level.txt
pyrecoil-0.3.11.dist-info/RECORD
