Metadata-Version: 2.1
Name: pyrecoil
Version: 0.3.11
Summary: Python bindings for RECOIL, the Retro Computer Image Library
Home-page: http://github.com/demozoo/pyrecoil
Author: Matt Westcott
Author-email: matt@west.co.tt
License: GPLv2+
Platform: UNKNOWN
Classifier: Development Status :: 5 - Production/Stable
Classifier: Topic :: Multimedia :: Graphics
Classifier: Topic :: Multimedia :: Graphics :: Graphics Conversion
Classifier: Programming Language :: Python :: 3
Classifier: Programming Language :: Python :: 3.8
Classifier: Programming Language :: Python :: 3.9
Classifier: Programming Language :: Python :: 3.10
Classifier: Programming Language :: Python :: 3.11
Classifier: Programming Language :: Python :: 3.12
Classifier: Programming Language :: Python :: 3.13
Classifier: License :: OSI Approved :: GNU General Public License v2 or later (GPLv2+)
Requires-Python: >=3.8
